Lab 5/half_adder.v
module half_adder (a,b,s,c);
input a;
input b;
output s;
output c;
assign s = a ^ b;
assign c = a & b;
endmodule

Lab 5/full_adder.v
`include "half_adder.v"

module full_adder (a,b,cin,sum,cout);

input a, b, cin;
output cout, sum;


wire s1, c1, c2;

half_adder ha1(a,b,s1,c1);
half_adder ha2(s1,cin,sum,c2);

or o1(cout,c1,c2);

endmodule

Lab 5/full_adder_tb.v
`timescale 1ns / 1ns
//Import the main code into the testbench
`include "full_adder.v"
module full_adder_verilog_tb;

reg a;
reg b;
reg cin;
wire sum;
wire cout;


full_adder uut(a,b,cin,sum,cout);
initial begin

    $dumpfile("full_adder_graph.vcd");
    $dumpvars(0,full_adder_verilog_tb);

a = 0;
b = 0;
cin = 0;
#10;

a = 0;
b = 0;
cin = 1;
#10;

a = 0;
b = 1;
cin = 0;
#10;

a = 0;
b = 1;
cin = 1;
#10;

a = 1;
b = 0;
cin = 0;
#10;

a = 1;
b = 0;
cin = 1;
#10;

a = 1;
b = 1;
cin = 0;
#10;

a = 1;
b = 1;
cin = 1;
#10;

a = 1;
b = 0;
cin = 0;


end

endmodule

Lab 5/full_adder_graph_2019AAPS0331H.vcd
$date
	Wed Sep 30 10:02:23 2020
$end
$version
	Icarus Verilog
$end
$timescale
	1ns
$end
$scope module full_adder_verilog_tb $end
$var wire 1 ! sum $end
$var wire 1 " cout $end
$var reg 1 # a $end
$var reg 1 $ b $end
$var reg 1 % cin $end
$scope module uut $end
$var wire 1 # a $end
$var wire 1 $ b $end
$var wire 1 % cin $end
$var wire 1 " cout $end
$var wire 1 ! sum $end
$var wire 1 & s1 $end
$var wire 1 ' c2 $end
$var wire 1 ( c1 $end
$scope module ha1 $end
$var wire 1 # a $end
$var wire 1 $ b $end
$var wire 1 ( c $end
$var wire 1 & s $end
$upscope $end
$scope module ha2 $end
$var wire 1 & a $end
$var wire 1 % b $end
$var wire 1 ' c $end
$var wire 1 ! s $end
$upscope $end
$upscope $end
$upscope $end
$enddefinitions $end
#0
$dumpvars
0(
0'
0&
0%
0$
0#
0"
0!
$end
#10
1!
1%
#20
1&
0%
1$
#30
1"
0!
1'
1%
#40
0"
1!
0'
0%
0$
1#
#50
1"
0!
1'
1%
#60
0'
0&
1(
0%
1$
#70
1!
1%
#80
0"
1&
0(
0%
0$
