Lab 10/JK Flip Flop/flipflop.v
module flipflop(d,clk,reset,q,qbar);

    input d, clk, reset;
    output reg q, qbar;
    
    always@(posedge clk)
        begin
        if(reset == 1)
            begin
                q <= 1'b0;
                qbar <= 1'b1;
            end
        else
            begin
                q <= d;      
                qbar <= ~d;  
            end 
        end
    
endmodule

Lab 10/JK Flip Flop/jkflipflop.v
`include "flipflop.v"

module jkflipflop (clk,reset,j,k,q,qbar);
input clk, reset, j, k;
output q, qbar;

wire w1, w2, w3, w4;

assign w4 = ~k;
assign w1 = w2 | w3;
assign w2 = qbar & j;
assign w3 = w4 & q;

flipflop da(w1, clk, reset, q, qbar);

endmodule

Lab 10/JK Flip Flop/jkflipflop_tb.v
`timescale 1ns / 1ns
`include "jkflipflop.v"
module jkflipflop_tb;
reg reset = 0;
reg clk = 0;
reg j = 0;
reg k = 0;
wire q;
wire qbar;

jkflipflop dut (.clk(clk), .reset(reset), .j(j), .k(k), .q(q), .qbar(qbar));

initial begin
    j = 0;
    repeat(4)

    #200 j = ~j;
end

initial begin
    k = 0;
    repeat(8)

    #100 k = ~k;
end

initial begin
    clk = 0;
    repeat(9)

    #115 clk = ~clk;
end

initial begin
    $dumpfile("jkflipflop.vcd");
    $dumpvars(0,jkflipflop_tb);
    reset = 0;

    #100 reset = ~reset;
    #100 reset = ~reset;
end
endmodule

Lab 10/JK Flip Flop/jkflipflop.vcd
$date
	Mon Nov  9 12:09:38 2020
$end
$version
	Icarus Verilog
$end
$timescale
	1ns
$end
$scope module jkflipflop_tb $end
$var wire 1 ! qbar $end
$var wire 1 " q $end
$var reg 1 # clk $end
$var reg 1 $ j $end
$var reg 1 % k $end
$var reg 1 & reset $end
$scope module dut $end
$var wire 1 # clk $end
$var wire 1 $ j $end
$var wire 1 % k $end
$var wire 1 & reset $end
$var wire 1 ' w1 $end
$var wire 1 ( w2 $end
$var wire 1 ) w3 $end
$var wire 1 * w4 $end
$var wire 1 ! qbar $end
$var wire 1 " q $end
$scope module da $end
$var wire 1 # clk $end
$var wire 1 ' d $end
$var wire 1 & reset $end
$var reg 1 " q $end
$var reg 1 ! qbar $end
$upscope $end
$upscope $end
$upscope $end
$enddefinitions $end
#0
$dumpvars
1*
x)
0(
x'
0&
0%
0$
0#
x"
x!
$end
#100
0'
0)
0*
1&
1%
#115
1!
0"
1#
#200
1'
1*
1(
0&
0%
1$
#230
0#
#300
0*
1%
#345
0'
0(
0!
1"
1#
#400
1'
1)
1*
0%
0$
#460
0#
#500
0'
0)
0*
1%
#575
1!
0"
1#
#600
1'
1*
1(
0%
1$
#690
0#
#700
0*
1%
#800
0'
1*
0(
0%
0$
