Lab 9/Parity Generator/decoder.v
module decoder(in,out);
input [2:0] in;
output [7:0] out;
wire [7:0] temp;
assign temp =
    (in == 3'b000 ) ? 8'b0000_0001 :
    (in == 3'b001 ) ? 8'b0000_0010 :
    (in == 3'b010 ) ? 8'b0000_0100 :
    (in == 3'b011 ) ? 8'b0000_1000 :
    (in == 3'b100 ) ? 8'b0001_0000 :
    (in == 3'b101 ) ? 8'b0010_0000 :
    (in == 3'b110 ) ? 8'b0100_0000 :
    (in == 3'b111 ) ? 8'b1000_0000 :
    8'h00;
assign out=temp;
endmodule

Lab 9/Parity Generator/odd_parity_generator.v
`include "decoder.v"

module parity (in,out);
input [2:0] in;
output out;
wire [7:0] temp;
decoder a(in,temp);
assign out = ((temp[0] | temp[3]) | (temp[5] | temp[6]));

endmodule

Lab 9/Parity Generator/odd_parity_tb.v
`timescale 1ns / 1ns
`include "odd_parity_generator.v"
module parity_tb;
reg [2:0] in;
wire out;
parity dut (.in(in),.out(out));
initial begin
    $dumpfile("parity_graph.vcd");
    $dumpvars(0,parity_tb);
in = 3'b000;
#10;
in = 3'b001;
#10;
in = 3'b010;
#10;
in = 3'b011;
#10;
in = 3'b100;
#10;
in = 3'b101;
#10;
in = 3'b110;
#10;
in = 3'b111;
#10;
in = 3'b000;
#10;
end
endmodule

Lab 9/Parity Generator/parity_graph.vcd
$date
	Mon Nov  2 14:18:33 2020
$end
$version
	Icarus Verilog
$end
$timescale
	1ns
$end
$scope module parity_tb $end
$var wire 1 ! out $end
$var reg 3 " in [2:0] $end
$scope module dut $end
$var wire 3 # in [2:0] $end
$var wire 1 ! out $end
$var wire 8 $ temp [7:0] $end
$scope module a $end
$var wire 3 % in [2:0] $end
$var wire 8 & out [7:0] $end
$var wire 8 ' temp [7:0] $end
$upscope $end
$upscope $end
$upscope $end
$enddefinitions $end
#0
$dumpvars
b1 '
b1 &
b0 %
b1 $
b0 #
b0 "
1!
$end
#10
0!
b10 $
b10 &
b10 '
b1 "
b1 #
b1 %
#20
b100 $
b100 &
b100 '
b10 "
b10 #
b10 %
#30
1!
b1000 $
b1000 &
b1000 '
b11 "
b11 #
b11 %
#40
0!
b10000 $
b10000 &
b10000 '
b100 "
b100 #
b100 %
#50
1!
b100000 $
b100000 &
b100000 '
b101 "
b101 #
b101 %
#60
b1000000 $
b1000000 &
b1000000 '
b110 "
b110 #
b110 %
#70
0!
b10000000 $
b10000000 &
b10000000 '
b111 "
b111 #
b111 %
#80
1!
b1 $
b1 &
b1 '
b0 "
b0 #
b0 %
