Lab 9/Full Adder/multiplexer.v
module multiplexer(I,S,Y);
input [7:0] I;
input [2:0] S;
output Y;
assign Y = I[S];
endmodule

Lab 9/Full Adder/full_adder.v
`include "multiplexer.v"
module full_adder(a,b,cin,sum,cout);
input a;
input b;
input cin;
output sum;
output cout;

wire [7:0] R1;
wire [7:0] R2;

assign R1 = 8'b1001_0110;
multiplexer m1(R1,{a,b,cin}, sum);
assign R2 = 8'b1110_1000;
multiplexer m2(R2,{a,b,cin}, cout);

endmodule

Lab 9/Full Adder/full_adder_tb.v
`timescale 1ns / 1ns
`include "full_adder.v"
module full_adder_tb;
reg a;
reg b;
reg cin;
wire sum;
wire cout;
full_adder dut (.a(a),.b(b), .cin(cin), .sum(sum), .cout(cout));
initial begin
    $dumpfile("full.vcd");
    $dumpvars(0,full_adder_tb);
a = 0;
b = 0;
cin = 0;
#10;
a = 0;
b = 0;
cin = 1;
#10;
a = 0;
b = 1;
cin = 0;
#10;
a = 0;
b = 1;
cin = 1;
#10;
a = 1;
b = 0;
cin = 0;
#10;
a = 1;
b = 0;
cin = 1;
#10;
a = 1;
b = 1;
cin = 0;
#10;
a = 1;
b = 1;
cin = 1;
#10;
a = 1;
b = 0;
cin = 0;
end
endmodule

Lab 9/Full Adder/full.vcd
$date
	Mon Nov  2 14:11:39 2020
$end
$version
	Icarus Verilog
$end
$timescale
	1ns
$end
$scope module full_adder_tb $end
$var wire 1 ! sum $end
$var wire 1 " cout $end
$var reg 1 # a $end
$var reg 1 $ b $end
$var reg 1 % cin $end
$scope module dut $end
$var wire 8 & R1 [7:0] $end
$var wire 8 ' R2 [7:0] $end
$var wire 1 # a $end
$var wire 1 $ b $end
$var wire 1 % cin $end
$var wire 1 ! sum $end
$var wire 1 " cout $end
$scope module m1 $end
$var wire 8 ( I [7:0] $end
$var wire 3 ) S [2:0] $end
$var wire 1 ! Y $end
$upscope $end
$scope module m2 $end
$var wire 8 * I [7:0] $end
$var wire 3 + S [2:0] $end
$var wire 1 " Y $end
$upscope $end
$upscope $end
$upscope $end
$enddefinitions $end
#0
$dumpvars
b0 +
b11101000 *
b0 )
b10010110 (
b11101000 '
b10010110 &
0%
0$
0#
0"
0!
$end
#10
1!
b1 )
b1 +
1%
#20
0%
1!
b10 )
0"
b10 +
1$
#30
0!
b11 )
1"
b11 +
1%
#40
0"
0%
0$
1!
b100 )
b100 +
1#
#50
0!
b101 )
1"
b101 +
1%
#60
0%
0!
b110 )
b110 +
1$
#70
1!
b111 )
b111 +
1%
#80
0"
0%
1!
b100 )
b100 +
0$
