Lab 4/Exp1 - Majority Circuit/2019AAPS0331H.v
module majority (A,B,C,F);

    //Inputs
    input A;
    input B;
    input C;
    
    //Outputs
    output F;

    //Components
    wire w1;
    wire w2;
    wire w3;
    wire w4;
    and g1(w1,A,B);
    and g2(w2,B,C);
    and g3(w3,A,C);
    or g4(w4,w1,w2);
    or g5(F,w3,w4);

endmodule

Lab 4/Exp1 - Majority Circuit/2019AAPS0331H_tb.v
`timescale 1ns / 1ns
//Import the main code into the testbench
`include "2019AAPS0331H.v"

module majority_tb;

//Inputs as registers
reg A;
reg B;
reg C;


//Ouputs as wires
wire F;

//Initialiastion
majority uut(A,B,C,F);

initial begin
    $dumpfile("2019AAPS0331H_tb.vcd");
    $dumpvars(0,majority_tb);
    // Uncomment a paritcular sequence of Test Bench Inputs for the required result
    // Even Parity
    A = 0;
    B = 0; 
    C = 0;
    #10;
    
    A = 0;
    B = 0; 
    C = 1;
    #10;

    A = 0;
    B = 1; 
    C = 0;
    #10;

    A = 0;
    B = 1; 
    C = 1;
    #10;

    A = 1;
    B = 0; 
    C = 0;
    #10;

    A = 1;
    B = 0; 
    C = 1;
    #10;

    A = 1;
    B = 1; 
    C = 0;
    #10;

    A = 1;
    B = 1; 
    C = 1;
    #10;

    $display("Test complete");
end

endmodule

Lab 4/Exp1 - Majority Circuit/2019AAPS0331H_tb.vcd
$date
	Mon Sep 21 12:13:53 2020
$end
$version
	Icarus Verilog
$end
$timescale
	1ns
$end
$scope module majority_tb $end
$var wire 1 ! F $end
$var reg 1 " A $end
$var reg 1 # B $end
$var reg 1 $ C $end
$scope module uut $end
$var wire 1 " A $end
$var wire 1 # B $end
$var wire 1 $ C $end
$var wire 1 ! F $end
$var wire 1 % w1 $end
$var wire 1 & w2 $end
$var wire 1 ' w3 $end
$var wire 1 ( w4 $end
$upscope $end
$upscope $end
$enddefinitions $end
#0
$dumpvars
0(
0'
0&
0%
0$
0#
0"
0!
$end
#10
1$
#20
0$
1#
#30
1!
1(
1&
1$
#40
0!
0(
0&
0$
0#
1"
#50
1!
1'
1$
#60
1(
0'
1%
0$
1#
#70
1&
1'
1$
