Lab 6/four_bit_adder.v
module four_bit_adder (a,b,s,c);
input [3:0] a;
input [3:0] b;
output [3:0] s;
output c;
assign {c,s} = a + b;
endmodule

Lab 6/four_bit_adder_tb.v
`timescale 1ns / 1ns
`include "four_bit_adder.v"
module four_bit_adder_tb;

reg [3:0] a;
reg [3:0] b;
wire [3:0] s;
wire c;

four_bit_adder dut (.a(a), .b(b), .s(s), .c(c));

initial begin

    $dumpfile("four_bit_adder_graph.vcd");
    $dumpvars(0,four_bit_adder_tb);


a = 4'b0000;
b = 4'b0000;
#10;

a = 4'b0001;
b = 4'b0001;
#10;

a = 4'b0010;
b = 4'b0010;
#10;

a = 4'b0011;
b = 4'b0011;
#10;

a = 4'b0100;
b = 4'b0100;
#10;

a = 4'b0101;
b = 4'b0101;
#10;

a = 4'b0110;
b = 4'b0110;
#10;

a = 4'b0111;
b = 4'b0111;
#10;


a = 4'b1000;
b = 4'b1000;
#10;

a = 4'b1001;
b = 4'b1001;
#10;

a = 4'b1010;

b = 4'b1010;
#10;

a = 4'b1011;
b = 4'b1011;
#10;

a = 4'b1100;
b = 4'b1100;
#10;

a = 4'b1101;
b = 4'b1101;
#10;

a = 4'b1110;
b = 4'b1110;
#10;

a = 4'b1111;
b = 4'b1111;
#10;

end

endmodule

Lab 6/four_bit_adder_graph.vcd
$date
	Mon Oct  5 10:04:57 2020
$end
$version
	Icarus Verilog
$end
$timescale
	1ns
$end
$scope module four_bit_adder_tb $end
$var wire 4 ! s [3:0] $end
$var wire 1 " c $end
$var reg 4 # a [3:0] $end
$var reg 4 $ b [3:0] $end
$scope module dut $end
$var wire 4 % a [3:0] $end
$var wire 4 & b [3:0] $end
$var wire 4 ' s [3:0] $end
$var wire 1 " c $end
$upscope $end
$upscope $end
$enddefinitions $end
#0
$dumpvars
b0 '
b0 &
b0 %
b0 $
b0 #
0"
b0 !
$end
#10
b10 !
b10 '
b1 $
b1 &
b1 #
b1 %
#20
b100 !
b100 '
b10 $
b10 &
b10 #
b10 %
#30
b110 !
b110 '
b11 $
b11 &
b11 #
b11 %
#40
b1000 !
b1000 '
b100 $
b100 &
b100 #
b100 %
#50
b1010 !
b1010 '
b101 $
b101 &
b101 #
b101 %
#60
b1100 !
b1100 '
b110 $
b110 &
b110 #
b110 %
#70
b1110 !
b1110 '
b111 $
b111 &
b111 #
b111 %
#80
1"
b0 !
b0 '
b1000 $
b1000 &
b1000 #
b1000 %
#90
b10 !
b10 '
b1001 $
b1001 &
b1001 #
b1001 %
#100
b100 !
b100 '
b1010 $
b1010 &
b1010 #
b1010 %
#110
b110 !
b110 '
b1011 $
b1011 &
b1011 #
b1011 %
#120
b1000 !
b1000 '
b1100 $
b1100 &
b1100 #
b1100 %
#130
b1010 !
b1010 '
b1101 $
b1101 &
b1101 #
b1101 %
#140
b1100 !
b1100 '
b1110 $
b1110 &
b1110 #
b1110 %
#150
b1110 !
b1110 '
b1111 $
b1111 &
b1111 #
b1111 %
