Lab 4/Exp2 - Parity Generator/2019AAPS0331H.v
module parity (A,B,C,I,P);

    //Inputs
    input A;
    input B;
    input C;
    input I;

    //Outputs
    output P;

    //Components
    wire w1;
    wire w2;
    xor g1(w1,A,B);
    xor g2(w2,w1,C);
    xor g3(P,I,w2);

endmodule

Lab 4/Exp2 - Parity Generator/2019AAPS0331H_tb.v
`timescale 1ns / 1ns
//Import the main code into the testbench
`include "2019AAPS0331H.v"

module parity_tb;

//Inputs as registers
reg A;
reg B;
reg C;
reg I;

//Ouputs as wires
wire P;

//Initialiastion
parity uut(A,B,C,I,P);

initial begin
    $dumpfile("2019AAPS0331H_tb.vcd");
    $dumpvars(0,parity_tb);
    // Uncomment a paritcular sequence of Test Bench Inputs for the required result
    // Even Parity
    A = 0;
    B = 0; 
    C = 0;
    I = 0;
    #10;
    
    A = 0;
    B = 0; 
    C = 1;
    I = 0;
    #10;

    A = 0;
    B = 1; 
    C = 0;
    I = 0;
    #10;

    A = 0;
    B = 1; 
    C = 1;
    I = 0;
    #10;

    A = 1;
    B = 0; 
    C = 0;
    I = 0;
    #10;

    A = 1;
    B = 0; 
    C = 1;
    I = 0;
    #10;

    A = 1;
    B = 1; 
    C = 0;
    I = 0;
    #10;

    A = 1;
    B = 1; 
    C = 1;
    I = 0;
    #10;
    

    // Odd Parity
    A = 0;
    B = 0; 
    C = 0;
    I = 1;
    #10;
    
    A = 0;
    B = 0; 
    C = 1;
    I = 1;
    #10;

    A = 0;
    B = 1; 
    C = 0;
    I = 1;
    #10;

    A = 0;
    B = 1; 
    C = 1;
    I = 1;
    #10;

    A = 1;
    B = 0; 
    C = 0;
    I = 1;
    #10;

    A = 1;
    B = 0; 
    C = 1;
    I = 1;
    #10;

    A = 1;
    B = 1; 
    C = 0;
    I = 1;
    #10;

    A = 1;
    B = 1; 
    C = 1;
    I = 1;
    #10;

    
    $display("Test complete");
end

endmodule

Lab 4/Exp2 - Parity Generator/2019AAPS0331H_tb.vcd
$date
	Mon Sep 21 10:24:40 2020
$end
$version
	Icarus Verilog
$end
$timescale
	1ns
$end
$scope module parity_tb $end
$var wire 1 ! P $end
$var reg 1 " A $end
$var reg 1 # B $end
$var reg 1 $ C $end
$var reg 1 % I $end
$scope module uut $end
$var wire 1 " A $end
$var wire 1 # B $end
$var wire 1 $ C $end
$var wire 1 % I $end
$var wire 1 ! P $end
$var wire 1 & w1 $end
$var wire 1 ' w2 $end
$upscope $end
$upscope $end
$enddefinitions $end
#0
$dumpvars
0'
0&
0%
0$
0#
0"
0!
$end
#10
1!
1'
1$
#20
1&
0$
1#
#30
0!
0'
1$
#40
1!
1'
0$
0#
1"
#50
0!
0'
1$
#60
0&
0$
1#
#70
1!
1'
1$
#80
0'
1%
0$
0#
0"
#90
0!
1'
1$
#100
1&
0$
1#
#110
1!
0'
1$
#120
0!
1'
0$
0#
1"
#130
1!
0'
1$
#140
0&
0$
1#
#150
0!
1'
1$
