Lab 10/Binary Counter/flipflop.v
module flipflop(d,clk,reset,q,qbar);

    input d, clk, reset;
    output reg q, qbar;
    
    always@(posedge clk)
        begin
        if(reset == 1)
            begin
                q <= 1'b0;
                qbar <= 1'b1;
            end
        else
            begin
                q <= d;      
                qbar <= ~d;  
            end 
        end

endmodule

Lab 10/Binary Counter/binarycounter.v
`include "flipflop.v"

module binarycounter (clk,reset,qa,qb);

input in, clk, reset;
output qa, qb;

wire w1, w2, w3, w4, w5, w6;

flipflop da(w1, clk, reset, w3, w4);
flipflop db(w2, clk, reset, w5, w6);

assign w1 = w4;
assign w2 = w3 ^ w5;

assign qa = w3;
assign qb = w5;

endmodule

Lab 10/Binary Counter/binarycounter_tb.v
`timescale 1ns / 1ns
`include "binarycounter.v"

module binarycounter_tb;
reg reset = 0;
reg clk = 0;
wire qa;
wire qb;

binarycounter dut (.clk(clk), .reset(reset), .qa(qa), .qb(qb));

initial begin
    clk = 0;
    repeat(12)

    #100 clk = ~clk;
end

initial begin
    $dumpfile("binarycounter.vcd");
    $dumpvars(0,binarycounter_tb);
    reset = 1;
    repeat(1)

    #200 reset = ~reset;

end
endmodule

Lab 10/Binary Counter/binarycounter.vcd
$date
	Mon Nov  9 13:49:26 2020
$end
$version
	Icarus Verilog
$end
$timescale
	1ns
$end
$scope module binarycounter_tb $end
$var wire 1 ! qb $end
$var wire 1 " qa $end
$var reg 1 # clk $end
$var reg 1 $ reset $end
$scope module dut $end
$var wire 1 # clk $end
$var wire 1 % in $end
$var wire 1 " qa $end
$var wire 1 ! qb $end
$var wire 1 $ reset $end
$var wire 1 & w1 $end
$var wire 1 ' w2 $end
$var wire 1 ( w6 $end
$var wire 1 ) w5 $end
$var wire 1 * w4 $end
$var wire 1 + w3 $end
$scope module da $end
$var wire 1 # clk $end
$var wire 1 & d $end
$var wire 1 $ reset $end
$var reg 1 + q $end
$var reg 1 * qbar $end
$upscope $end
$scope module db $end
$var wire 1 # clk $end
$var wire 1 ' d $end
$var wire 1 $ reset $end
$var reg 1 ) q $end
$var reg 1 ( qbar $end
$upscope $end
$upscope $end
$upscope $end
$enddefinitions $end
#0
$dumpvars
x+
x*
x)
x(
x'
x&
z%
1$
0#
x"
x!
$end
#100
0'
1&
1*
0"
0+
1(
0!
0)
1#
#200
0#
0$
#300
1'
0&
0*
1"
1+
1#
#400
0#
#500
1&
1*
0"
0+
0(
1!
1)
1#
#600
0#
#700
0'
0&
0*
1"
1+
1#
#800
0#
#900
1&
1*
0"
0+
1(
0!
0)
1#
#1000
0#
#1100
1'
0&
0*
1"
1+
1#
