Lab 10/Binary Counter/flipflop.v
module flipflop(d,clk,reset,q,qbar);

    input d, clk, reset;
    output reg q, qbar;
    
    always@(posedge clk)
        begin
        if(reset == 1)
            begin
                q <= 1'b0;
                qbar <= 1'b1;
            end
        else
            begin
                q <= d;      
                qbar <= ~d;  
            end 
        end

endmodule

Lab 10/T Flip Flop/tflipflop.v
`include "flipflop.v"

module tflipflop (clk,reset,t,q,qbar);
input clk, reset, t;
output q, qbar;

wire w1;

flipflop da(w1, clk, reset, q, qbar);
assign w1 = t ^ q;

endmodule

Lab 10/T Flip Flop/tflipflop_tb.v
`timescale 1ns / 1ns
`include "tflipflop.v"
module tflipflop_tb;
reg reset = 0;
reg clk = 0;
reg t = 0;
wire q;
wire qbar;

tflipflop dut (.clk(clk), .reset(reset), .t(t), .q(q), .qbar(qbar));

initial begin
    t = 0;
    repeat(12)

    #215 t = ~t;
end

initial begin
    clk = 0;
    repeat(12)

    #100 clk = ~clk;
end

initial begin
    $dumpfile("tflipflop.vcd");
    $dumpvars(0,tflipflop_tb);
    reset = 0;

    #100 reset = ~reset;
    #100 reset = ~reset;
end
endmodule

Lab 10/T Flip Flop/tflipflop.vcd
$date
	Mon Nov  9 13:56:55 2020
$end
$version
	Icarus Verilog
$end
$timescale
	1ns
$end
$scope module tflipflop_tb $end
$var wire 1 ! qbar $end
$var wire 1 " q $end
$var reg 1 # clk $end
$var reg 1 $ reset $end
$var reg 1 % t $end
$scope module dut $end
$var wire 1 # clk $end
$var wire 1 $ reset $end
$var wire 1 % t $end
$var wire 1 & w1 $end
$var wire 1 ! qbar $end
$var wire 1 " q $end
$scope module da $end
$var wire 1 # clk $end
$var wire 1 & d $end
$var wire 1 $ reset $end
$var reg 1 " q $end
$var reg 1 ! qbar $end
$upscope $end
$upscope $end
$upscope $end
$enddefinitions $end
#0
$dumpvars
x&
0%
0$
0#
x"
x!
$end
#100
0&
1!
0"
1$
1#
#200
0$
0#
#215
1&
1%
#300
0&
0!
1"
1#
#400
0#
#430
1&
0%
#500
1#
#600
0#
#645
0&
1%
#700
1&
1!
0"
1#
#800
0#
#860
0&
0%
#900
1#
#1000
0#
#1075
1&
1%
#1100
0&
0!
1"
1#
#1200
0#
#1290
1&
0%
#1505
0&
1%
#1720
1&
0%
#1935
0&
1%
#2150
1&
0%
#2365
0&
1%
#2580
1&
0%
